Workbook

Sheet Group Member Details
A1: Group: | B1: 23 (WE ARE THE EMPIRES)
A3: Companies: | B3: QL RESOURCES BERHAD
B4: UNITED PLANTATIONS BERHAD
A6: Group Members details | B6: Matric Number
A7: SHOBANA A/P MOHAN | B7: 152692
A8: MUHAMMAD HAIQAL BIN RAFIQUZZAMAN | B8: 158852
A9: DOROTHEA JONG KAI XIN | B9: 152076
A10: KAUSLYA A/P KANAKA MANI | B10: 153465
A11: LEE SOON KEAT | B11: 158717
A12: ANJUMANARA ATHINA | B12: 155142
A13: KHAUSAALYAAH A/P SINATHURAI | B13: 159355
A14: NUR ATIQAH | B14: 152264
A15: ZHAO YULIN | B15: 145328
A16: SWASTIKA A/P SINAPAN | B16: 152596

Sheet (A) Ratio analysis
A1: (A) Ratio Analysis excel sheet
B2: Working Capital | C2: Current ratio | D2: Acid test (Quick) ratio | E2: Inventory turnover ratio | F2: Accounts receivable turnover (times) | G2: Assets turnover ratio | H2: Debts to assets ratio | I2: Debts to equity ratio | J2: Times interest earned (times) | K2: Net profit margin (%) | L2: Returns on equity (%) | M2: Earnings per share (EPS) | N2: Price earnings ratio (PE ratio)
A3: Formula | B3: Total Current assets - Total Current Liabilities | C3: (Current assets / Current liabilities) | D3: [(Current assets-Inventories) / Current liabilities] | E3: (Cost of Goods Sold / Inventories) | F3: (Annual Credit Sales / Account receivables) | G3: (Net Sales / Total assets) | H3: (Total debt / Total assets) | I3: (Total debt / Total equities) | J3: (EBIT / Interest Expense) | K3: (Net income / Sales) | L3: (Net income / Shareholder's equity) | M3: [(Net income-Preferred dividends) / Average outstanding shares] | N3: (Market price per share / EPS)
A4: QL Resources Berhad
A5: 2020 | B5: ='(B) Working sheet'!B4-'(B) Working sheet'!C4 -> 418553000 | C5: ='(B) Working sheet'!B4/'(B) Working sheet'!C4 -> 1.3887156 | D5: =('(B) Working sheet'!B4-'(B) Working sheet'!G4)/'(B) Working sheet'!C4 -> 0.92775171 | E5: ='(B) Working sheet'!N4/'(B) Working sheet'!G4 -> 6.7085366 | G5: ='(B) Working sheet'!O4/'(B) Working sheet'!D4 -> 1.0219965 | H5: ='(B) Working sheet'!M4/'(B) Working sheet'!D4 -> 0.48577974 | I5: ='(B) Working sheet'!M4/'(B) Working sheet'!F4 -> 0.94469238 | J5: ='(B) Working sheet'!K4/'(B) Working sheet'!L4 -> 8.0556013 | K5: ='(B) Working sheet'!J4/'(B) Working sheet'!I4 -> 0.057501686 | L5: 19.95
A6: 2019 | B6: ='(B) Working sheet'!B5-'(B) Working sheet'!C5 -> 506450000 | C6: ='(B) Working sheet'!B5/'(B) Working sheet'!C5 -> 1.5243763 | D6: =('(B) Working sheet'!B5-'(B) Working sheet'!G5)/'(B) Working sheet'!C5 -> 0.93125488 | E6: ='(B) Working sheet'!N5/'(B) Working sheet'!G5 -> 5.1188088 | G6: ='(B) Working sheet'!O5/'(B) Working sheet'!D5 -> 0.98246093 | H6: ='(B) Working sheet'!M5/'(B) Working sheet'!D5 -> 0.45316738 | I6: ='(B) Working sheet'!M5/'(B) Working sheet'!F5 -> 0.82871314 | J6: ='(B) Working sheet'!K5/'(B) Working sheet'!L5 -> 4.9877421 | K6: ='(B) Working sheet'!J5/'(B) Working sheet'!I5 -> 0.062299723
A7: 2018 | B7: ='(B) Working sheet'!B6-'(B) Working sheet'!C6 -> 463871000 | C7: ='(B) Working sheet'!B6/'(B) Working sheet'!C6 -> 1.5881225 | D7: =('(B) Working sheet'!B6-'(B) Working sheet'!G6)/'(B) Working sheet'!C6 -> 1.1110415 | E7: ='(B) Working sheet'!N6/'(B) Working sheet'!G6 -> 7.0628108 | F7: 8.5 | G7: ='(B) Working sheet'!O6/'(B) Working sheet'!D6 -> 0.98112581 | H7: ='(B) Working sheet'!M6/'(B) Working sheet'!D6 -> 0.43145592 | I7: ='(B) Working sheet'!M6/'(B) Working sheet'!F6 -> 0.75887856 | J7: ='(B) Working sheet'!K6/'(B) Working sheet'!L6 -> 5.6889216 | K7: ='(B) Working sheet'!J6/'(B) Working sheet'!I6 -> 0.066093826 | L7: 11.41
A8: 2017 | B8: ='(B) Working sheet'!B7-'(B) Working sheet'!C7 -> 347898000 | C8: ='(B) Working sheet'!B7/'(B) Working sheet'!C7 -> 1.3853942 | D8: =('(B) Working sheet'!B7-'(B) Working sheet'!G7)/'(B) Working sheet'!C7 -> 0.93593713 | E8: ='(B) Working sheet'!N7/'(B) Working sheet'!G7 -> 6.0814733 | F8: 8 | G8: ='(B) Working sheet'!O7/'(B) Working sheet'!D7 -> 0.94719155 | H8: ='(B) Working sheet'!M7/'(B) Working sheet'!D7 -> 0.42086375 | I8: ='(B) Working sheet'!M7/'(B) Working sheet'!F7 -> 0.72670939 | J8: ='(B) Working sheet'!K7/'(B) Working sheet'!L7 -> 8.4087218 | K8: ='(B) Working sheet'!J7/'(B) Working sheet'!I7 -> 0.068664746 | L8: 11.83
A9: 2016 | B9: ='(B) Working sheet'!B8-'(B) Working sheet'!C8 -> 337149000 | C9: ='(B) Working sheet'!B8/'(B) Working sheet'!C8 -> 1.4459029 | D9: =('(B) Working sheet'!B8-'(B) Working sheet'!G8)/'(B) Working sheet'!C8 -> 0.94960746 | E9: ='(B) Working sheet'!N8/'(B) Working sheet'!G8 -> 6.2154025 | G9: ='(B) Working sheet'!O8/'(B) Working sheet'!D8 -> 1.0153778 | H9: ='(B) Working sheet'!M8/'(B) Working sheet'!D8 -> 0.12056881 | I9: ='(B) Working sheet'!M8/'(B) Working sheet'!F8 -> 0.2027663 | J9: ='(B) Working sheet'!K8/'(B) Working sheet'!L8 -> 6.9470094 | K9: ='(B) Working sheet'!J8/'(B) Working sheet'!I8 -> 0.079609664 | L9: 13.6 | M9: - | N9: -
A10: United Plantations Berhad
A11: 2020 | B11: ='(B) Working sheet'!B10-'(B) Working sheet'!C10 -> 795259000 | C11: ='(B) Working sheet'!B10/'(B) Working sheet'!C10 -> 5.4902489 | D11: =('(B) Working sheet'!B10-'(B) Working sheet'!G10)/'(B) Working sheet'!C10 -> 4.7311019 | E11: ='(B) Working sheet'!N10/'(B) Working sheet'!G10 -> 0.098035716 | G11: ='(B) Working sheet'!O10/'(B) Working sheet'!D10 -> 0.45002351 | H11: ='(B) Working sheet'!M10/'(B) Working sheet'!D10 -> 0.031941453 | I11: ='(B) Working sheet'!M10/'(B) Working sheet'!F10 -> 0.036117257 | J11: ='(B) Working sheet'!K10/'(B) Working sheet'!L10 -> 172.29063 | K11: ='(B) Working sheet'!J10/'(B) Working sheet'!I10 -> 0.29967136
A12: 2019 | B12: ='(B) Working sheet'!B11-'(B) Working sheet'!C11 -> 747113000 | C12: ='(B) Working sheet'!B11/'(B) Working sheet'!C11 -> 6.8961503 | D12: =('(B) Working sheet'!B11-'(B) Working sheet'!G11)/'(B) Working sheet'!C11 -> 5.9202049 | E12: ='(B) Working sheet'!N11/'(B) Working sheet'!G11 -> 0.12498383 | G12: ='(B) Working sheet'!O11/'(B) Working sheet'!D11 -> 0.40990431 | H12: ='(B) Working sheet'!M11/'(B) Working sheet'!D11 -> 0.032155429 | I12: ='(B) Working sheet'!M11/'(B) Working sheet'!F11 -> 0.035988571 | J12: ='(B) Working sheet'!K11/'(B) Working sheet'!L11 -> 46.928853 | K12: ='(B) Working sheet'!J11/'(B) Working sheet'!I11 -> 0.24237129
A13: 2018 | B13: ='(B) Working sheet'!B12-'(B) Working sheet'!C12 -> 1186146000 | C13: ='(B) Working sheet'!B12/'(B) Working sheet'!C12 -> 7.9828335 | D13: =('(B) Working sheet'!B12-'(B) Working sheet'!G12)/'(B) Working sheet'!C12 -> 7.0829124 | E13: ='(B) Working sheet'!N12/'(B) Working sheet'!G12 -> 0.14201327 | G13: ='(B) Working sheet'!O12/'(B) Working sheet'!D12 -> 0.44679616 | H13: ='(B) Working sheet'!M12/'(B) Working sheet'!D12 -> 0.047090707 | I13: ='(B) Working sheet'!M12/'(B) Working sheet'!F12 -> 0.053083587 | J13: ='(B) Working sheet'!K12/'(B) Working sheet'!L12 -> 72.815866 | K13: ='(B) Working sheet'!J12/'(B) Working sheet'!I12 -> 0.2865369
A14: 2017 | B14: ='(B) Working sheet'!B13-'(B) Working sheet'!C13 -> 1140875000 | C14: ='(B) Working sheet'!B13/'(B) Working sheet'!C13 -> 7.9641135 | D14: =('(B) Working sheet'!B13-'(B) Working sheet'!G13)/'(B) Working sheet'!C13 -> 7.0067756 | E14: ='(B) Working sheet'!N13/'(B) Working sheet'!G13 -> 0.11415965 | F14: 8.74 | G14: ='(B) Working sheet'!O13/'(B) Working sheet'!D13 -> 0.51683808 | H14: ='(B) Working sheet'!M13/'(B) Working sheet'!D13 -> 0.048375987 | I14: ='(B) Working sheet'!M13/'(B) Working sheet'!F13 -> 0.054472507 | J14: ='(B) Working sheet'!K13/'(B) Working sheet'!L13 -> 45.770204 | K14: ='(B) Working sheet'!J13/'(B) Working sheet'!I13 -> 0.26770389 | L14: 0.16
A15: 2016 | B15: ='(B) Working sheet'!B14-'(B) Working sheet'!C14 -> 1040567000 | C15: ='(B) Working sheet'!B14/'(B) Working sheet'!C14 -> 8.140768 | D15: =('(B) Working sheet'!B14-'(B) Working sheet'!G14)/'(B) Working sheet'!C14 -> 6.8372037 | E15: ='(B) Working sheet'!N14/'(B) Working sheet'!G14 -> 0.38052622 | G15: ='(B) Working sheet'!O14/'(B) Working sheet'!D14 -> 0.46439159 | H15: ='(B) Working sheet'!M14/'(B) Working sheet'!D14 -> 0.043343361 | I15: ='(B) Working sheet'!M14/'(B) Working sheet'!F14 -> 0.048365706 | J15: ='(B) Working sheet'!K14/'(B) Working sheet'!L14 -> 12.143757 | K15: ='(B) Working sheet'!J14/'(B) Working sheet'!I14 -> 0.2693026

Sheet (B) Working sheet
A1: (B) Working sheet
B2: Current assets (RM) | C2: Current liabilities (RM) | D2: Total assets (RM) | E2: Total liabilities (RM) | F2: Total equities (RM) | G2: Inventories (RM) | H2: Account receivables (RM) | I2: Total sales (RM) | J2: Net income (RM) | K2: Net operating income/EBIT (RM) | L2: Interest Expense (RM) | M2: Total debt (RM) | N2: Cost of Goods Sold (RM) | O2: Net Sales (RM) | P2: Preferred Dividends (RM)
A3: QL Resources Berhad
A4: 2020 | B4: 1495312000 | C4: 1076759000 | D4: 4066380000 | E4: 1975365000 | F4: 2091014000 | G4: 496347000 | H4: 358150000 | I4: 4155826000 | J4: 238967000 | K4: 528238000 | L4: 65574000 | M4: 1975365000 | N4: 3329762000 | O4: 4155826000
A5: 2019 | B5: 1472264000 | C5: 965814000 | D5: 3683661000 | E5: 1669315000 | F5: 2014346000 | G5: 572845000 | H5: 308928000 | I5: 3619053000 | J5: 225466000 | K5: 291748000 | L5: 58493000 | M5: 1669315000 | N5: 2932284000 | O5: 3619053000
A6: 2018 | B6: 1252603000 | C6: 788732000 | D6: 3325918000 | E6: 1434987000 | F6: 1890931000 | G6: 376289000 | H6: 383986000 | I6: 3263270000 | J6: 215682000 | K6: 259119000 | L6: 45548000 | M6: 1434987000 | N6: 2657658000 | O6: 3263144000
A7: 2017 | B7: 1250605000 | C7: 902707000 | D7: 3179927000 | E7: 1338316000 | F7: 1841611000 | G7: 405728000 | H7: 378597000 | I7: 3012026000 | J7: 206820000 | K7: 310635000 | L7: 36942000 | M7: 1338316000 | N7: 2467424000 | O7: 3012000000
A8: 2016 | B8: 1093253000 | C8: 756104000 | D8: 2810022000 | E8: 1139128000 | F8: 1670894000 | G8: 375251000 | H8: 338801000 | I8: 2853234000 | J8: 227145000 | K8: 249481000 | L8: 35912000 | M8: 338801000 | N8: 2332336000 | O8: 2853234000
A9: United Plantations Berhad
A10: 2020 | B10: 972367000 | C10: 177108000 | D10: 2974849000 | E10: 343946000 | F10: 2630903000 | G10: 134451000 | H10: 186853000 | I10: 1340058000 | J10: 401577000 | K10: 385931000 | L10: 2240000 | M10: 95021000 | N10: 13181000 | O10: 1338752000 | P10: 89900
A11: 2019 | B11: 873825000 | C11: 126712000 | D11: 2858211000 | E11: 304428000 | F11: 2553783000 | G11: 123664000 | H11: 157966000 | I11: 1173101000 | J11: 284326000 | K11: 285609000 | L11: 6086000 | M11: 91907000 | N11: 15456000 | O11: 1171593000 | P11: 89900
A12: 2018 | B12: 1356012000 | C12: 169866000 | D12: 2918389000 | E12: 329472000 | F12: 2588917000 | G12: 152866000 | H12: 133712000 | I12: 1305591000 | J12: 374100000 | K12: 523182000 | L12: 7185000 | M12: 137429000 | N12: 21709000 | O12: 1303925000 | P12: 324800
A13: 2017 | B13: 1304697000 | C13: 163822000 | D13: 2849761000 | E13: 318943000 | F13: 2530818000 | G13: 156833000 | H13: 168602000 | I13: 1474323000 | J13: 394682000 | K13: 568054000 | L13: 12411000 | M13: 137860000 | N13: 17904000 | O13: 1472865000 | P13: 349800
A14: 2016 | B14: 1186289000 | C14: 145722000 | D14: 2641904000 | E14: 274338000 | F14: 2367566000 | G14: 189958000 | H14: 181875000 | I14: 1228384000 | J14: 330807000 | K14: 213888000 | L14: 17613000 | M14: 114509000 | N14: 72284000 | O14: 1226878000 | P14: 404826
